setup.py
binandgaus_distributions/Binomialdistribution.py
binandgaus_distributions/Gaussiandistribution.py
binandgaus_distributions/Generaldistribution.py
binandgaus_distributions/__init__.py
binandgaus_distributions.egg-info/PKG-INFO
binandgaus_distributions.egg-info/SOURCES.txt
binandgaus_distributions.egg-info/dependency_links.txt
binandgaus_distributions.egg-info/not-zip-safe
binandgaus_distributions.egg-info/top_level.txt